orthoflow/__init__.py
orthoflow/config/config.yml
orthoflow/main.py
orthoflow/profiles/local/config.yaml
orthoflow/profiles/slurm/config.yaml
orthoflow/profiles/slurm/slurm-cancel
orthoflow/workflow/Snakefile
orthoflow/workflow/__init__.py
orthoflow/workflow/bibs/TranslatorX.nbib
orthoflow/workflow/bibs/astral-iii.ris
orthoflow/workflow/bibs/biokit.bib
orthoflow/workflow/bibs/biopython.bib
orthoflow/workflow/bibs/clipkit.bib
orthoflow/workflow/bibs/ete.ris
orthoflow/workflow/bibs/gbseqextractor.bib
orthoflow/workflow/bibs/iqtree2.bib
orthoflow/workflow/bibs/mafft7.bib
orthoflow/workflow/bibs/modelfinder.ris
orthoflow/workflow/bibs/orthofinder.ris
orthoflow/workflow/bibs/orthofisher.nbib
orthoflow/workflow/bibs/phykit.bib
orthoflow/workflow/bibs/toytree.bib
orthoflow/workflow/bibs/ultrafast-bootstrap.bib
orthoflow/workflow/envs/astral.yaml
orthoflow/workflow/envs/biokit.yaml
orthoflow/workflow/envs/biopython.yaml
orthoflow/workflow/envs/clipkit.yaml
orthoflow/workflow/envs/ete.yaml
orthoflow/workflow/envs/iqtree.yaml
orthoflow/workflow/envs/jinja.yaml
orthoflow/workflow/envs/joblib.yaml
orthoflow/workflow/envs/mafft.yaml
orthoflow/workflow/envs/matplotlib.yaml
orthoflow/workflow/envs/orthofinder.yaml
orthoflow/workflow/envs/orthofisher.yaml
orthoflow/workflow/envs/orthosnap.yaml
orthoflow/workflow/envs/perl.yaml
orthoflow/workflow/envs/phykit.yaml
orthoflow/workflow/envs/samtools.yaml
orthoflow/workflow/envs/seaborn.yaml
orthoflow/workflow/envs/summary.yaml
orthoflow/workflow/envs/toytree.yaml
orthoflow/workflow/envs/typer.yaml
orthoflow/workflow/report/alignment.html
orthoflow/workflow/report/alignment_summary.rst
orthoflow/workflow/report/assets/css/bootstrap.cosmo.min.css
orthoflow/workflow/report/assets/img/orthoflow-favicon.png
orthoflow/workflow/report/assets/img/orthoflow-logo-black.svg
orthoflow/workflow/report/assets/img/orthoflow-logo-blue.svg
orthoflow/workflow/report/assets/img/orthoflow-logo-white-on-blue.svg
orthoflow-0.3.4.dist-info/LICENSE
orthoflow-0.3.4.dist-info/METADATA
orthoflow-0.3.4.dist-info/WHEEL
orthoflow-0.3.4.dist-info/entry_points.txt
orthoflow-0.3.4.dist-info/RECORD
