Metadata-Version: 2.1
Name: orthoflow
Version: 0.3.4
Summary: A phylogenomic workflow
Home-page: https://github.com/rbturnbull/orthoflow
License: Apache-2.0
Keywords: phylogenomics
Author: Robert Turnbull
Requires-Python: >=3.8,<3.12
Classifier: Intended Audience :: Science/Research
Classifier: License :: OSI Approved :: Apache Software License
Classifier: Programming Language :: Python :: 3
Classifier: Programming Language :: Python :: 3.8
Classifier: Programming Language :: Python :: 3.9
Classifier: Programming Language :: Python :: 3.10
Classifier: Programming Language :: Python :: 3.11
Classifier: Topic :: Scientific/Engineering :: Bio-Informatics
Classifier: Topic :: Software Development :: Libraries :: Python Modules
Requires-Dist: Flask (>=2.1.2)
Requires-Dist: Jinja2 (>=3.1.2)
Requires-Dist: appdirs (>=1.4.4)
Requires-Dist: biopython (>=1.79)
Requires-Dist: joblib (>=1.2.0)
Requires-Dist: pandas (>=1.2.5)
Requires-Dist: phytest (>=1.4.1)
Requires-Dist: pulp (==2.7.0)
Requires-Dist: pydot (>=1.4.2)
Requires-Dist: rich (>=13.3.3)
Requires-Dist: snakemake (>=7.0.0)
Requires-Dist: toml (>=0.10.2)
Requires-Dist: typer (>=0.4.1)
Project-URL: Documentation, https://rbturnbull.github.io/orthoflow/
Project-URL: Repository, https://github.com/rbturnbull/orthoflow
